animal_language/__init__.py
animal_language/core.py
animal_language-0.1.2.dist-info/LICENSE
animal_language-0.1.2.dist-info/WHEEL
animal_language-0.1.2.dist-info/METADATA
animal_language-0.1.2.dist-info/RECORD
