Metadata-Version: 2.1
Name: animal-language
Version: 0.1.2
Summary: Customize a word set, and then use the words in this set to represent any sentence.
Home-page: https://github.com/chnzzh/animal-language
Author: chnzzh
Author-email: chnzzh@outlook.com
Requires-Python: >=3.6,<4.0
Classifier: Programming Language :: Python :: 3
Classifier: Programming Language :: Python :: 3.10
Classifier: Programming Language :: Python :: 3.6
Classifier: Programming Language :: Python :: 3.7
Classifier: Programming Language :: Python :: 3.8
Classifier: Programming Language :: Python :: 3.9
Project-URL: Bug Tracker, https://github.com/chnzzh/animal-language/issues
Project-URL: Repository, https://github.com/chnzzh/animal-language
